kanggenetools/__init__.py
kanggenetools/authorization.cpython-38-darwin.so
kanggenetools/authorization.py
kanggenetools/compression_algorithm.cpython-38-darwin.so
kanggenetools/main.py
kanggenetools/transform.py
kanggenetools-0.16.dist-info/METADATA
kanggenetools-0.16.dist-info/WHEEL
kanggenetools-0.16.dist-info/top_level.txt
kanggenetools-0.16.dist-info/RECORD
